sptag/CSHARPSPTAG.dll
sptag/CSHARPSPTAGClient.dll
sptag/Microsoft.ANN.SPTAGManaged.dll
sptag/SPTAG.dll
sptag/SPTAG.py
sptag/SPTAGClient.py
sptag/Server.exe
sptag/_SPTAG.exp
sptag/_SPTAG.lib
sptag/_SPTAG.pdb
sptag/_SPTAG.pyd
sptag/_SPTAGClient.exp
sptag/_SPTAGClient.lib
sptag/_SPTAGClient.pdb
sptag/_SPTAGClient.pyd
sptag/__init__.py
sptag/libzstd.dll
sptag/version.py
sptag/SPTAG.WinRT/SPTAG.dll
sptag/SPTAG.WinRT/libzstd.dll
sptag-1.6.8.dist-info/LICENSE
sptag-1.6.8.dist-info/METADATA
sptag-1.6.8.dist-info/WHEEL
sptag-1.6.8.dist-info/top_level.txt
sptag-1.6.8.dist-info/RECORD
