Metadata-Version: 2.1
Name: sptag
Version: 1.6.8
Summary: SPTAG: A library for fast approximate nearest neighbor search
Home-page: https://github.com/Microsoft/SPTAG
Author: Microsoft SPTAG Team
Author-email: cheqi@microsoft.com
License: MIT
Platform: UNKNOWN
Classifier: License :: OSI Approved :: MIT License
Classifier: Operating System :: Microsoft :: Windows :: Windows 10
Classifier: Operating System :: POSIX :: Linux
Classifier: Programming Language :: Python :: 3
Classifier: Intended Audience :: Science/Research
Requires-Python: >=3.6
License-File: LICENSE
Requires-Dist: numpy
